masstransitpython/RabbitMQConfiguration.py
masstransitpython/RabbitMQReceiver.py
masstransitpython/RabbitMQSender.py
masstransitpython/__init__.py
src/RabbitMQConfiguration.py
src/RabbitMQReceiver.py
src/RabbitMQSender.py
src/__init__.py
masstransitpython_byQ96-0.0.4.dist-info/LICENSE
masstransitpython_byQ96-0.0.4.dist-info/METADATA
masstransitpython_byQ96-0.0.4.dist-info/WHEEL
masstransitpython_byQ96-0.0.4.dist-info/top_level.txt
masstransitpython_byQ96-0.0.4.dist-info/RECORD
