Metadata-Version: 2.1
Name: masstransitpython-byQ96
Version: 0.0.4
Summary: Python RabbitMQ client for MassTransit Communication
Home-page: https://github.com/byQ96/MassTransitPython
Author: Michał Wieczorek
Author-email: michal126@hotmail.com
License: UNKNOWN
Platform: UNKNOWN
Classifier: Programming Language :: Python :: 3
Classifier: License :: OSI Approved :: MIT License
Classifier: Operating System :: OS Independent
Requires-Python: >=3.7
